odoo/addons/fieldservice_recurring/README.rst
odoo/addons/fieldservice_recurring/__init__.py
odoo/addons/fieldservice_recurring/__manifest__.py
odoo/addons/fieldservice_recurring/data/ir_sequence.xml
odoo/addons/fieldservice_recurring/data/recurring_cron.xml
odoo/addons/fieldservice_recurring/demo/frequency_demo.xml
odoo/addons/fieldservice_recurring/demo/frequency_set_demo.xml
odoo/addons/fieldservice_recurring/demo/recur_template_demo.xml
odoo/addons/fieldservice_recurring/i18n/de.po
odoo/addons/fieldservice_recurring/i18n/es.po
odoo/addons/fieldservice_recurring/i18n/es_AR.po
odoo/addons/fieldservice_recurring/i18n/es_CL.po
odoo/addons/fieldservice_recurring/i18n/fieldservice_recurring.pot
odoo/addons/fieldservice_recurring/i18n/it.po
odoo/addons/fieldservice_recurring/i18n/pt_BR.po
odoo/addons/fieldservice_recurring/i18n/sv.po
odoo/addons/fieldservice_recurring/i18n/tr.po
odoo/addons/fieldservice_recurring/models/__init__.py
odoo/addons/fieldservice_recurring/models/fsm_frequency.py
odoo/addons/fieldservice_recurring/models/fsm_frequency_set.py
odoo/addons/fieldservice_recurring/models/fsm_order.py
odoo/addons/fieldservice_recurring/models/fsm_recurring.py
odoo/addons/fieldservice_recurring/models/fsm_recurring_template.py
odoo/addons/fieldservice_recurring/models/fsm_team.py
odoo/addons/fieldservice_recurring/readme/CONFIGURE.md
odoo/addons/fieldservice_recurring/readme/CONTRIBUTORS.md
odoo/addons/fieldservice_recurring/readme/CREDITS.md
odoo/addons/fieldservice_recurring/readme/DESCRIPTION.md
odoo/addons/fieldservice_recurring/readme/INSTALL.md
odoo/addons/fieldservice_recurring/readme/ROADMAP.md
odoo/addons/fieldservice_recurring/readme/USAGE.md
odoo/addons/fieldservice_recurring/security/ir.model.access.csv
odoo/addons/fieldservice_recurring/security/recurring_security.xml
odoo/addons/fieldservice_recurring/security/res_groups.xml
odoo/addons/fieldservice_recurring/static/description/icon.png
odoo/addons/fieldservice_recurring/static/description/index.html
odoo_addon_fieldservice_recurring-18.0.1.2.0.dist-info/METADATA
odoo_addon_fieldservice_recurring-18.0.1.2.0.dist-info/WHEEL
odoo_addon_fieldservice_recurring-18.0.1.2.0.dist-info/top_level.txt
odoo_addon_fieldservice_recurring-18.0.1.2.0.dist-info/RECORD
